LICENSE
MANIFEST.in
README
greptable.py
run_tests.sh
setup.cfg
setup.py
test.py
greptable.egg-info/PKG-INFO
greptable.egg-info/SOURCES.txt
greptable.egg-info/dependency_links.txt
greptable.egg-info/entry_points.txt
greptable.egg-info/top_level.txt