Metadata-Version: 1.1
Name: greptable
Version: 1.1.0
Summary: List tables of SQL databases for easy schema greps
Home-page: http://git.p.engu.in/laurentb/greptable/
Author: Laurent Bachelier
Author-email: laurent@bachelier.name
License: UNKNOWN
Platform: UNKNOWN
Classifier: License :: OSI Approved :: MIT License
Classifier: Programming Language :: Python :: 2
Classifier: Programming Language :: Python :: 3
